gguf_cua/__init__.py
gguf_cua/__main__.py
gguf_cua/_prompts.py
gguf_cua/api_setting.py
gguf_cua/gguf_agent.py
gguf_cua/utils.py
gguf_cua/browser/__init__.py
gguf_cua/browser/browser_bb.py
gguf_cua/browser/page_script.js
gguf_cua/browser/playwright_controller.py
gguf_cua/helpers/__init__.py
gguf_cua/helpers/base_tool.py
gguf_cua/helpers/fncall_prompt.py
gguf_cua/helpers/schema.py
gguf_cua/helpers/utils.py
gguf_cua-0.1.3.dist-info/entry_points.txt
gguf_cua-0.1.3.dist-info/LICENSE
gguf_cua-0.1.3.dist-info/WHEEL
gguf_cua-0.1.3.dist-info/METADATA
gguf_cua-0.1.3.dist-info/RECORD
