Metadata-Version: 2.1
Name: gguf-cua
Version: 0.1.3
Summary: gguf computer use agent
Author-email: calcuis <info@calcu.io>
Classifier: License :: OSI Approved :: MIT License
Project-URL: Issues, https://github.com/calcuis/gguf-cua/issues
Project-URL: Repository, https://github.com/calcuis/gguf-cua
